{
  "culture": "zh-Hans",
  "texts": {
    "Menu:Home": "首页",
    "Welcome": "欢迎",
    "LongWelcomeMessage": "欢迎来到该应用程序. 这是一个基于ABP框架的启动项目. 有关更多信息, 请访问 abp.io.",
    "DisplayName:BaseService.SpecialSwitch.ShowStore": "显示门店列表",
    "Description:BaseService.SpecialSwitch.ShowStore": "【商城设置-平台设置-特殊开关】显示门店列表！",
    "DisplayName:BaseService.SpecialSwitch.ShowCharge": "显示充值功能",
    "Description:BaseService.SpecialSwitch.ShowCharge": "【商城设置-平台设置-特殊开关】显示充值功能！",

    "DisplayName:BaseService.PlatformSetting.ShopName": "平台名称",
    "Description:BaseService.PlatformSetting.ShopName": "【商城设置-平台设置-平台设置】平台名称！",
    "DisplayName:BaseService.PlatformSetting.ShopDesc": "平台描述",
    "Description:BaseService.PlatformSetting.ShopDesc": "【商城设置-平台设置-平台设置】平台描述！",
    "DisplayName:BaseService.PlatformSetting.ShopBeiAn": "备案信息",
    "Description:BaseService.PlatformSetting.ShopBeiAn": "【商城设置-平台设置-平台设置】备案信息！",
    "DisplayName:BaseService.PlatformSetting.AboutArticle": "关于我们",
    "Description:BaseService.PlatformSetting.AboutArticle": "【商城设置-平台设置-平台设置】关于我们！",
    "DisplayName:BaseService.PlatformSetting.UserAgreement": "用户协议",
    "Description:BaseService.PlatformSetting.UserAgreement": "【商城设置-平台设置-平台设置】用户协议！",
    "DisplayName:BaseService.PlatformSetting.PrivacyPolicy": "隐私政策",
    "Description:BaseService.PlatformSetting.PrivacyPolicy": "【商城设置-平台设置-平台设置】隐私政策！",
    "DisplayName:BaseService.PlatformSetting.PlatformLogo": "平台Logo",
    "Description:BaseService.PlatformSetting.PlatformLogo": "【商城设置-平台设置-平台设置】平台Logo！",
    "DisplayName:BaseService.PlatformSetting.DefaultPic": "默认图片",
    "Description:BaseService.PlatformSetting.DefaultPic": "【商城设置-平台设置-平台设置】默认图片！",
    "DisplayName:BaseService.PlatformSetting.StoreSwitch": "开启门店自提",
    "Description:BaseService.PlatformSetting.StoreSwitch": "【商城设置-平台设置-平台设置】开启门店自提！",
    "DisplayName:BaseService.PlatformSetting.InvoiceSwitch": "发票功能",
    "Description:BaseService.PlatformSetting.InvoiceSwitch": "【商城设置-平台设置-平台设置】发票功能！",
    "DisplayName:BaseService.PlatformSetting.RecommendKeys": "搜索发现关键词",
    "Description:BaseService.PlatformSetting.RecommendKeys": "【商城设置-平台设置-平台设置】搜索发现关键词！",

    "DisplayName:BaseService.ShareSetting.ShareTitle": "分享标题",
    "Description:BaseService.ShareSetting.ShareTitle": "【商城设置-平台设置-分享设置】分享标题！",
    "DisplayName:BaseService.ShareSetting.ShareDesc": "分享描述",
    "Description:BaseService.ShareSetting.ShareDesc": "【商城设置-平台设置-分享设置】分享描述！",
    "DisplayName:BaseService.ShareSetting.ShareImage": "分享图片",
    "Description:BaseService.ShareSetting.ShareImage": "【商城设置-平台设置-分享设置】分享图片！",

    "DisplayName:BaseService.UsersSetting.IsBindMobile": "绑定手机号码",
    "Description:BaseService.UsersSetting.IsBindMobile": "【商城设置-平台设置-会员设置】绑定手机号码！",
    "DisplayName:BaseService.UsersSetting.ShopMobile": "商家手机号码",
    "Description:BaseService.UsersSetting.ShopMobile": "【商城设置-平台设置-会员设置】商家手机号码！",

    "DisplayName:BaseService.GoodsSetting.GoodsStocksWarn": "库存警报数量",
    "Description:BaseService.GoodsSetting.GoodsStocksWarn": "【商城设置-商品设置-商品设置】库存警报数量！",

    "DisplayName:BaseService.OrderSetting.OrderCancelTime": "订单取消时间",
    "Description:BaseService.OrderSetting.OrderCancelTime": "【商城设置-商品设置-订单设置】订单取消时间！",
    "DisplayName:BaseService.OrderSetting.OrderCompleteTime": "订单完成时间",
    "Description:BaseService.OrderSetting.OrderCompleteTime": "【商城设置-商品设置-订单设置】订单完成时间！",
    "DisplayName:BaseService.OrderSetting.OrderAutoSignTime": "订单确认收货时间",
    "Description:BaseService.OrderSetting.OrderAutoSignTime": "【商城设置-商品设置-订单设置】订单确认收货时间！",
    "DisplayName:BaseService.OrderSetting.OrderAutoEvalTime": "订单自动评价时间",
    "Description:BaseService.OrderSetting.OrderAutoEvalTime": "【商城设置-商品设置-订单设置】订单自动评价时间！",
    "DisplayName:BaseService.OrderSetting.RemindOrderTime": "订单提醒付款时间",
    "Description:BaseService.OrderSetting.RemindOrderTime": "【商城设置-商品设置-订单设置】订单提醒付款时间！",
    "DisplayName:BaseService.OrderSetting.ReshipName": "退货联系人",
    "Description:BaseService.OrderSetting.ReshipName": "【商城设置-商品设置-订单设置】退货联系人！",
    "DisplayName:BaseService.OrderSetting.ReshipMobile": "退货联系方式",
    "Description:BaseService.OrderSetting.ReshipMobile": "【商城设置-商品设置-订单设置】退货联系方式！",
    "DisplayName:BaseService.OrderSetting.ReshipAreaId": "退货区域",
    "Description:BaseService.OrderSetting.ReshipAreaId": "【商城设置-商品设置-订单设置】退货区域！",
    "DisplayName:BaseService.OrderSetting.ReshipCoordinate": "退货坐标",
    "Description:BaseService.OrderSetting.ReshipCoordinate": "【商城设置-商品设置-订单设置】退货坐标！",
    "DisplayName:BaseService.OrderSetting.ReshipAddress": "退货详细地址",
    "Description:BaseService.OrderSetting.ReshipAddress": "【商城设置-商品设置-订单设置】退货详细地址！",
    "DisplayName:BaseService.OrderSetting.StoreOrderAutomaticDelivery": "门店自提自动发货",
    "Description:BaseService.OrderSetting.StoreOrderAutomaticDelivery": "【商城设置-商品设置-订单设置】门店自提自动发货！",

    "DisplayName:BaseService.PointsSetting.PointSwitch": "开启积分功能",
    "Description:BaseService.PointsSetting.PointSwitch": "【商城设置-商品设置-积分设置】开启积分功能！",
    "DisplayName:BaseService.PointsSetting.PointDiscountedProportion": "订单积分折现比例",
    "Description:BaseService.PointsSetting.PointDiscountedProportion": "【商城设置-商品设置-积分设置】订单积分折现比例！",
    "DisplayName:BaseService.PointsSetting.OrdersPointProportion": "订单积分使用比例",
    "Description:BaseService.PointsSetting.OrdersPointProportion": "【商城设置-商品设置-积分设置】订单积分使用比例！",
    "DisplayName:BaseService.PointsSetting.OrdersRewardProportion": "订单积分奖励比例",
    "Description:BaseService.PointsSetting.OrdersRewardProportion": "【商城设置-商品设置-积分设置】订单积分奖励比例！",
    "DisplayName:BaseService.PointsSetting.SignPointType": "签到奖励类型",
    "Description:BaseService.PointsSetting.SignPointType": "【商城设置-商品设置-积分设置】签到奖励类型！",
    "DisplayName:BaseService.PointsSetting.FirstSignPoint": "首次奖励积分",
    "Description:BaseService.PointsSetting.FirstSignPoint": "【商城设置-商品设置-积分设置】首次奖励积分！",
    "DisplayName:BaseService.PointsSetting.ContinuitySignAdditional": "连续签到追加",
    "Description:BaseService.PointsSetting.ContinuitySignAdditional": "【商城设置-商品设置-积分设置】连续签到追加！",
    "DisplayName:BaseService.PointsSetting.SignMostPoint": "单日最大奖励",
    "Description:BaseService.PointsSetting.SignMostPoint": "【商城设置-商品设置-积分设置】单日最大奖励！",
    "DisplayName:BaseService.PointsSetting.SignRandomMin": "随机奖励积分最小值",
    "Description:BaseService.PointsSetting.SignRandomMin": "【商城设置-商品设置-积分设置】随机奖励积分最小值！",
    "DisplayName:BaseService.PointsSetting.SignRandomMax": "随机奖励积分最大值",
    "Description:BaseService.PointsSetting.SignRandomMax": "【商城设置-商品设置-积分设置】随机奖励积分最大值！",

    "DisplayName:BaseService.CashSetting.TocashMoneyLow": "最低提现金额",
    "Description:BaseService.CashSetting.TocashMoneyLow": "【商城设置-商品设置-提现设置】最低提现金额！",
    "DisplayName:BaseService.CashSetting.TocashMoneyRate": "提现服务费率",
    "Description:BaseService.CashSetting.TocashMoneyRate": "【商城设置-商品设置-提现设置】提现服务费率！",
    "DisplayName:BaseService.CashSetting.TocashMoneyLimit": "每日提现上限",
    "Description:BaseService.CashSetting.TocashMoneyLimit": "【商城设置-商品设置-提现设置】每日提现上限！",

    "DisplayName:BaseService.InviteFriendSetting.CommissionType": "佣金类型",
    "Description:BaseService.InviteFriendSetting.CommissionType": "【商城设置-商品设置-邀请好友设置】佣金类型！",
    "DisplayName:BaseService.InviteFriendSetting.CommissionFirst": "一级佣金",
    "Description:BaseService.InviteFriendSetting.CommissionFirst": "【商城设置-商品设置-邀请好友设置】一级佣金！",
    "DisplayName:BaseService.InviteFriendSetting.CommissionSecond": "二级佣金",
    "Description:BaseService.InviteFriendSetting.CommissionSecond": "【商城设置-商品设置-邀请好友设置】二级佣金！",
    "DisplayName:BaseService.InviteFriendSetting.CommissionThird": "三级佣金",
    "Description:BaseService.InviteFriendSetting.CommissionThird": "【商城设置-商品设置-邀请好友设置】三级佣金！",

    "DisplayName:BaseService.FileStorageSetting.StorageType": "存储方式",
    "Description:BaseService.FileStorageSetting.StorageType": "【商城设置-商品设置-附件设置】存储方式！",
    "DisplayName:BaseService.FileStorageSetting.StoragePath": "存储路径",
    "Description:BaseService.FileStorageSetting.StoragePath": "【商城设置-商品设置-附件设置】存储路径！",
    "DisplayName:BaseService.FileStorageSetting.StorageSuffix": "文件后缀类型",
    "Description:BaseService.FileStorageSetting.StorageSuffix": "【商城设置-商品设置-附件设置】文件后缀类型！",
    "DisplayName:BaseService.FileStorageSetting.StorageMaxSize": "文件最大大小",
    "Description:BaseService.FileStorageSetting.StorageMaxSize": "【商城设置-商品设置-附件设置】文件最大大小！",
    "DisplayName:BaseService.FileStorageSetting.StorageServerJson": "存储服务[Json对象]",
    "Description:BaseService.FileStorageSetting.StorageServerJson": "【商城设置-商品设置-附件设置】存储服务[Json对象]！",

    "DisplayName:EasyAbp.Abp.WeChat.Official.AppId": "AppID",
    "Description:EasyAbp.Abp.WeChat.Official.AppId": "【商城设置-平台设置-微信平台】微信公众号AppID！",
    "DisplayName:EasyAbp.Abp.WeChat.Official.AppSecret": "AppSecret",
    "Description:EasyAbp.Abp.WeChat.Official.AppSecret": "【商城设置-平台设置-微信平台】微信公众号AppSecret！",
    "DisplayName:EasyAbp.Abp.WeChat.Official.Token": "Token",
    "Description:EasyAbp.Abp.WeChat.Official.Token": "【商城设置-平台设置-微信平台】微信公众号Token！",
    "DisplayName:EasyAbp.Abp.WeChat.Official.EncodingAesKey": "EncodingAesKey",
    "Description:EasyAbp.Abp.WeChat.Official.EncodingAesKey": "【商城设置-平台设置-微信平台】微信公众号EncodingAesKey！",
    "DisplayName:EasyAbp.Abp.WeChat.Official.OAuthRedirectUrl": "OAuthRedirectUrl",
    "Description:EasyAbp.Abp.WeChat.Official.OAuthRedirectUrl": "【商城设置-平台设置-微信平台】微信公众号OAuthRedirectUrl！",

    "DisplayName:EasyAbp.Abp.WeChat.MiniProgram.AppId": "AppID",
    "Description:EasyAbp.Abp.WeChat.MiniProgram.AppId": "【商城设置-平台设置-微信平台】微信小程序AppID！",
    "DisplayName:EasyAbp.Abp.WeChat.MiniProgram.AppSecret": "AppSecret",
    "Description:EasyAbp.Abp.WeChat.MiniProgram.AppSecret": "【商城设置-平台设置-微信平台】微信小程序AppSecret！",
    "DisplayName:EasyAbp.Abp.WeChat.MiniProgram.Token": "Token",
    "Description:EasyAbp.Abp.WeChat.MiniProgram.Token": "【商城设置-平台设置-微信平台】微信小程序Token！",
    "DisplayName:EasyAbp.Abp.WeChat.MiniProgram.EncodingAesKey": "EncodingAesKey",
    "Description:EasyAbp.Abp.WeChat.MiniProgram.EncodingAesKey": "【商城设置-平台设置-微信平台】微信小程序EncodingAesKey！",

    "DisplayName:EasyAbp.Abp.WeChat.Pay.MchId": "商户ID",
    "Description:EasyAbp.Abp.WeChat.Pay.MchId": "【商城设置-平台设置-微信平台】微信支付商户ID！",
    "DisplayName:EasyAbp.Abp.WeChat.Pay.ApiKey": "ApiKey",
    "Description:EasyAbp.Abp.WeChat.Pay.ApiKey": "【商城设置-平台设置-微信平台】微信支付ApiKey！",
    "DisplayName:EasyAbp.Abp.WeChat.Pay.IsSandBox": "是否沙箱环境",
    "Description:EasyAbp.Abp.WeChat.Pay.IsSandBox": "【商城设置-平台设置-微信平台】微信支付商户[是否沙箱环境]！",
    "DisplayName:EasyAbp.Abp.WeChat.Pay.NotifyUrl": "通知链接",
    "Description:EasyAbp.Abp.WeChat.Pay.NotifyUrl": "【商城设置-平台设置-微信平台】微信支付商户通知链接！",
    "DisplayName:EasyAbp.Abp.WeChat.Pay.RefundNotifyUrl": "退款通知链接",
    "Description:EasyAbp.Abp.WeChat.Pay.RefundNotifyUrl": "【商城设置-平台设置-微信平台】微信支付退款通知链接！",
    "DisplayName:EasyAbp.Abp.WeChat.Pay.CertificateSecret": "API证书密钥",
    "Description:EasyAbp.Abp.WeChat.Pay.CertificateSecret": "【商城设置-平台设置-微信平台】微信支付证书Secret！",
    "DisplayName:EasyAbp.Abp.WeChat.Pay.CertificateBlobName": "证书Blob名称",
    "Description:EasyAbp.Abp.WeChat.Pay.CertificateBlobName": "【商城设置-平台设置-微信平台】微信支付证书Blob名称！",
    "DisplayName:EasyAbp.Abp.WeChat.Pay.CertificateBlobContainerName": "Blob容器名称",
    "Description:EasyAbp.Abp.WeChat.Pay.CertificateBlobContainerName": "【商城设置-平台设置-微信平台】微信支付Blob容器名称！",
    "DisplayName:EasyAbp.Abp.WeChat.Pay.AcceptLanguage": "语言语种",
    "Description:EasyAbp.Abp.WeChat.Pay.AcceptLanguage": "【商城设置-平台设置-微信平台】微信支付语言语种！",

    "DisplayName:BaseService.OtherSetting.EntId": "客服ID",
    "Description:BaseService.OtherSetting.EntId": "【商城设置-商品设置-其它设置】客服ID！",
    "DisplayName:BaseService.OtherSetting.QqMapKey": "腾讯地图Key",
    "Description:BaseService.OtherSetting.QqMapKey": "【商城设置-商品设置-其它设置】腾讯地图Key！",
    "DisplayName:BaseService.OtherSetting.ShowApiAppId": "AppId",
    "Description:BaseService.OtherSetting.ShowApiAppId": "【商城设置-商品设置-其它设置】[易源]AppId！",
    "DisplayName:BaseService.OtherSetting.ShowApiSecret": "授权Secret",
    "Description:BaseService.OtherSetting.ShowApiSecret": "【商城设置-商品设置-其它设置】[易源]授权Secret！",
    "DisplayName:BaseService.OtherSetting.Kuaidi100Customer": "公司编号",
    "Description:BaseService.OtherSetting.Kuaidi100Customer": "【商城设置-商品设置-其它设置】[快递100]公司编号！",
    "DisplayName:BaseService.OtherSetting.Kuaidi100Key": "授权Key",
    "Description:BaseService.OtherSetting.Kuaidi100Key": "【商城设置-商品设置-其它设置】[快递100]授权Key！",
    "DisplayName:BaseService.OtherSetting.StatisticsCode": "百度统计代码",
    "Description:BaseService.OtherSetting.StatisticsCode": "【商城设置-商品设置-其它设置】[统计代码]百度统计代码！"
  }
}